{
  "dataSetElements": [
    {
      "dataElement": {
        "name":"RDIM_5.3_The inventory records are up to date\n(MOV-Inventory book)",
        "id":"cUGyymMtx1Z",
        "optionSet": {
          "name":"KQMH_3 Scoring Options(Yes, No, P)",
          "options":[ {
            "code": "3", "name": "Yes", "id": "t6ItoVnIYTv"
          }
          ,
            {
              "code": "1", "name": "Partial", "id": "QBoQanfiVfd"
            }
          ,
            {
              "code": "0", "name": "No", "id": "owtmpRi3xjk"
            }
          ]
        }
      }
    }
  ,
    {
      "dataElement": {
        "name":"RDIM_5.3_The facility has qualified personnel designated to handle procurement\n(MOV-HR records)",
        "id":"dnkfjZv9REW",
        "optionSet": {
          "name":"KQMH_1 Scoring Options(Yes, No)",
          "options":[ {
            "code": "3", "name": "Yes", "id": "nPYuVhUac6d"
          }
          ,
            {
              "code": "0", "name": "No", "id": "ZiXq4b0DCeq"
            }
          ]
        }
      }
    }
  ,
    {
      "dataElement": {
        "name":"RDIM_5.2_The facility carries out the prequalification of suppliers\n(MOV-List of pre-qualified suppliers/vendors, licences of supplies)",
        "id":"KP4THpvfVuv",
        "optionSet": {
          "name":"KQMH_1 Scoring Options(Yes, No)",
          "options":[ {
            "code": "3", "name": "Yes", "id": "nPYuVhUac6d"
          }
          ,
            {
              "code": "0", "name": "No", "id": "ZiXq4b0DCeq"
            }
          ]
        }
      }
    }
  ,
    {
      "dataElement": {
        "name":"RDIM_5.1_The procurement plan is incorporated in the facility budget.\n(MOV-Approved budget)",
        "id":"AEiavKiOj9L",
        "optionSet": {
          "name":"KQMH_1 Scoring Options(Yes, No)",
          "options":[ {
            "code": "3", "name": "Yes", "id": "nPYuVhUac6d"
          }
          ,
            {
              "code": "0", "name": "No", "id": "ZiXq4b0DCeq"
            }
          ]
        }
      }
    }
  ,
    {
      "dataElement": {
        "name":"RDIM_5.3_Specifications for all products and services to be procured are in place\n(MOV-List/log sheet of specifications)",
        "id":"YWX0cRV6ps5",
        "optionSet": {
          "name":"KQMH_3 Scoring Options(Yes, No, P)",
          "options":[ {
            "code": "3", "name": "Yes", "id": "t6ItoVnIYTv"
          }
          ,
            {
              "code": "1", "name": "Partial", "id": "QBoQanfiVfd"
            }
          ,
            {
              "code": "0", "name": "No", "id": "owtmpRi3xjk"
            }
          ]
        }
      }
    }
  ,
    {
      "dataElement": {
        "name":"RDIM_5.3_An inventory management system is in place\n(MOV-confirm for paper based or electronic system)",
        "id":"CENkip8JhOz",
        "optionSet": {
          "name":"KQMH_1 Scoring Options(Yes, No)",
          "options":[ {
            "code": "3", "name": "Yes", "id": "nPYuVhUac6d"
          }
          ,
            {
              "code": "0", "name": "No", "id": "ZiXq4b0DCeq"
            }
          ]
        }
      }
    }
  ,
    {
      "dataElement": {
        "name":"RDIM_5.2_The facility evaluates performance of suppliers annually (MOV- Minutes of evaluation meetings)",
        "id":"bAqZudv1KD1",
        "optionSet": {
          "name":"KQMH_1 Scoring Options(Yes, No)",
          "options":[ {
            "code": "3", "name": "Yes", "id": "nPYuVhUac6d"
          }
          ,
            {
              "code": "0", "name": "No", "id": "ZiXq4b0DCeq"
            }
          ]
        }
      }
    }
  ,
    {
      "dataElement": {
        "name":"RDIM_5.3_Goods stored according to manufacturer’s specification(MOV-sample 3 items each from pharmacy stores, laboratory, general store and food store)",
        "id":"WrdBTlIXzpI",
        "optionSet": {
          "name":"KQMH_3 Scoring Options(Yes, No, P)",
          "options":[ {
            "code": "3", "name": "Yes", "id": "t6ItoVnIYTv"
          }
          ,
            {
              "code": "1", "name": "Partial", "id": "QBoQanfiVfd"
            }
          ,
            {
              "code": "0", "name": "No", "id": "owtmpRi3xjk"
            }
          ]
        }
      }
    }
  ,
    {
      "dataElement": {
        "name":"RDIM_5.1_The facility has an approved procurement plan(MOV-Documented plan for current financial/calendar year, minutes)",
        "id":"qaCmPxW3GvS",
        "optionSet": {
          "name":"KQMH_1 Scoring Options(Yes, No)",
          "options":[ {
            "code": "3", "name": "Yes", "id": "nPYuVhUac6d"
          }
          ,
            {
              "code": "0", "name": "No", "id": "ZiXq4b0DCeq"
            }
          ]
        }
      }
    }

  ]
}